{"nodes": [{"name": "奥运_4"}, {"name": "起始页_4"}, {"name": "起始页_5"}, {"name": "起始页_0"}, {"name": "起始页_1"}, {"name": "奥运_0"}, {"name": "起始页_3"}, {"name": "互动_6"}, {"name": "跳出"}, {"name": "互动_5"}, {"name": "互动_2"}, {"name": "互动_3"}, {"name": "互动_0"}, {"name": "互动_1"}, {"name": "直播_6"}, {"name": "直播_4"}, {"name": "直播_5"}, {"name": "直播_2"}, {"name": "直播_3"}, {"name": "直播_0"}, {"name": "直播_1"}, {"name": "其他_2"}, {"name": "其他_3"}, {"name": "其他_0"}, {"name": "其他_1"}, {"name": "其他_6"}, {"name": "其他_4"}, {"name": "其他_5"}, {"name": "点播_0"}, {"name": "奥运_3"}, {"name": "点播_4"}, {"name": "点播_5"}, {"name": "点播_6"}, {"name": "奥运_2"}, {"name": "奥运_5"}, {"name": "点播_1"}, {"name": "点播_2"}, {"name": "点播_3"}, {"name": "起始页_2"}, {"name": "商城_2"}, {"name": "奥运_6"}, {"name": "商城_6"}, {"name": "商城_5"}, {"name": "商城_4"}, {"name": "商城_3"}, {"name": "互动_4"}, {"name": "商城_1"}, {"name": "商城_0"}, {"name": "奥运_1"}], "links": [{"source": 11, "target": 26, "value": 672}, {"source": 10, "target": 22, "value": 149}, {"source": 13, "target": 21, "value": 54}, {"source": 12, "target": 24, "value": 16}, {"source": 9, "target": 25, "value": 585}, {"source": 45, "target": 27, "value": 498}, {"source": 36, "target": 8, "value": 797}, {"source": 37, "target": 8, "value": 1261}, {"source": 4, "target": 36, "value": 12}, {"source": 35, "target": 8, "value": 1908}, {"source": 32, "target": 8, "value": 545}, {"source": 30, "target": 34, "value": 28}, {"source": 31, "target": 8, "value": 1578}, {"source": 33, "target": 22, "value": 128}, {"source": 29, "target": 26, "value": 869}, {"source": 5, "target": 24, "value": 12}, {"source": 48, "target": 21, "value": 64}, {"source": 0, "target": 27, "value": 116}, {"source": 34, "target": 25, "value": 377}, {"source": 2, "target": 25, "value": 245}, {"source": 0, "target": 8, "value": 41}, {"source": 27, "target": 8, "value": 802}, {"source": 16, "target": 32, "value": 1723}, {"source": 15, "target": 31, "value": 6511}, {"source": 11, "target": 15, "value": 221}, {"source": 20, "target": 36, "value": 1675}, {"source": 19, "target": 35, "value": 72}, {"source": 18, "target": 30, "value": 3159}, {"source": 17, "target": 37, "value": 2365}, {"source": 28, "target": 20, "value": 70}, {"source": 36, "target": 29, "value": 6}, {"source": 27, "target": 14, "value": 1190}, {"source": 26, "target": 16, "value": 3644}, {"source": 22, "target": 15, "value": 2362}, {"source": 21, "target": 18, "value": 22691}, {"source": 24, "target": 17, "value": 3045}, {"source": 23, "target": 20, "value": 597}, {"source": 47, "target": 20, "value": 1}, {"source": 28, "target": 48, "value": 4}, {"source": 24, "target": 8, "value": 4294}, {"source": 3, "target": 35, "value": 211}, {"source": 6, "target": 26, "value": 248}, {"source": 38, "target": 22, "value": 377}, {"source": 15, "target": 34, "value": 1}, {"source": 30, "target": 8, "value": 767}, {"source": 1, "target": 31, "value": 15}, {"source": 23, "target": 48, "value": 6}, {"source": 24, "target": 33, "value": 172}, {"source": 21, "target": 29, "value": 1166}, {"source": 22, "target": 0, "value": 128}, {"source": 26, "target": 34, "value": 488}, {"source": 27, "target": 40, "value": 111}, {"source": 21, "target": 44, "value": 33}, {"source": 22, "target": 43, "value": 209}, {"source": 23, "target": 46, "value": 4}, {"source": 24, "target": 39, "value": 17}, {"source": 26, "target": 42, "value": 82}, {"source": 27, "target": 41, "value": 95}, {"source": 31, "target": 14, "value": 5189}, {"source": 30, "target": 16, "value": 2549}, {"source": 13, "target": 17, "value": 32}, {"source": 12, "target": 20, "value": 21}, {"source": 35, "target": 17, "value": 2260}, {"source": 3, "target": 20, "value": 2137}, {"source": 37, "target": 15, "value": 1918}, {"source": 36, "target": 18, "value": 1378}, {"source": 27, "target": 25, "value": 1680}, {"source": 26, "target": 27, "value": 2383}, {"source": 22, "target": 26, "value": 2180}, {"source": 21, "target": 22, "value": 4764}, {"source": 24, "target": 21, "value": 38209}, {"source": 23, "target": 24, "value": 6041}, {"source": 34, "target": 8, "value": 103}, {"source": 37, "target": 45, "value": 1}, {"source": 38, "target": 29, "value": 1}, {"source": 10, "target": 8, "value": 23}, {"source": 11, "target": 8, "value": 53}, {"source": 45, "target": 8, "value": 88}, {"source": 9, "target": 8, "value": 71}, {"source": 7, "target": 8, "value": 72}, {"source": 6, "target": 0, "value": 3}, {"source": 42, "target": 8, "value": 18}, {"source": 6, "target": 30, "value": 23}, {"source": 3, "target": 46, "value": 1}, {"source": 4, "target": 33, "value": 5}, {"source": 26, "target": 8, "value": 1723}, {"source": 1, "target": 27, "value": 256}, {"source": 25, "target": 8, "value": 1178}, {"source": 4, "target": 21, "value": 320}, {"source": 3, "target": 24, "value": 40465}, {"source": 21, "target": 8, "value": 5714}, {"source": 22, "target": 8, "value": 926}, {"source": 0, "target": 9, "value": 4}, {"source": 34, "target": 7, "value": 13}, {"source": 17, "target": 44, "value": 1}, {"source": 29, "target": 45, "value": 3}, {"source": 48, "target": 10, "value": 2}, {"source": 44, "target": 8, "value": 11}, {"source": 39, "target": 8, "value": 3}, {"source": 46, "target": 8, "value": 5}, {"source": 2, "target": 40, "value": 2}, {"source": 37, "target": 0, "value": 7}, {"source": 41, "target": 8, "value": 24}, {"source": 3, "target": 48, "value": 89}, {"source": 43, "target": 8, "value": 48}, {"source": 24, "target": 36, "value": 742}, {"source": 23, "target": 35, "value": 30}, {"source": 22, "target": 30, "value": 615}, {"source": 21, "target": 37, "value": 4273}, {"source": 27, "target": 32, "value": 600}, {"source": 26, "target": 31, "value": 2190}, {"source": 48, "target": 8, "value": 145}, {"source": 31, "target": 32, "value": 1482}, {"source": 30, "target": 31, "value": 1495}, {"source": 37, "target": 30, "value": 1556}, {"source": 36, "target": 37, "value": 732}, {"source": 35, "target": 36, "value": 993}, {"source": 28, "target": 35, "value": 5129}, {"source": 35, "target": 21, "value": 242}, {"source": 28, "target": 24, "value": 81}, {"source": 45, "target": 16, "value": 351}, {"source": 20, "target": 17, "value": 7607}, {"source": 35, "target": 33, "value": 3}, {"source": 2, "target": 14, "value": 62}, {"source": 19, "target": 20, "value": 10647}, {"source": 10, "target": 18, "value": 57}, {"source": 16, "target": 7, "value": 203}, {"source": 15, "target": 9, "value": 136}, {"source": 18, "target": 45, "value": 382}, {"source": 17, "target": 11, "value": 60}, {"source": 20, "target": 10, "value": 64}, {"source": 19, "target": 13, "value": 8}, {"source": 18, "target": 26, "value": 4663}, {"source": 17, "target": 22, "value": 1153}, {"source": 20, "target": 21, "value": 932}, {"source": 19, "target": 24, "value": 282}, {"source": 29, "target": 8, "value": 189}, {"source": 16, "target": 25, "value": 2675}, {"source": 15, "target": 27, "value": 1134}, {"source": 33, "target": 8, "value": 51}, {"source": 9, "target": 14, "value": 117}, {"source": 18, "target": 15, "value": 17881}, {"source": 17, "target": 18, "value": 7213}, {"source": 37, "target": 26, "value": 2579}, {"source": 36, "target": 22, "value": 491}, {"source": 31, "target": 25, "value": 1915}, {"source": 30, "target": 27, "value": 524}, {"source": 16, "target": 14, "value": 8487}, {"source": 15, "target": 16, "value": 10118}, {"source": 9, "target": 7, "value": 1}, {"source": 45, "target": 9, "value": 6}, {"source": 11, "target": 45, "value": 6}, {"source": 10, "target": 11, "value": 4}, {"source": 13, "target": 10, "value": 3}, {"source": 12, "target": 13, "value": 60}, {"source": 1, "target": 16, "value": 81}, {"source": 40, "target": 8, "value": 32}, {"source": 4, "target": 10, "value": 1}, {"source": 20, "target": 8, "value": 3072}, {"source": 17, "target": 8, "value": 2099}, {"source": 18, "target": 8, "value": 5081}, {"source": 15, "target": 8, "value": 4365}, {"source": 16, "target": 8, "value": 3470}, {"source": 14, "target": 8, "value": 3468}, {"source": 38, "target": 37, "value": 10}, {"source": 46, "target": 21, "value": 10}, {"source": 39, "target": 22, "value": 11}, {"source": 44, "target": 26, "value": 18}, {"source": 43, "target": 27, "value": 119}, {"source": 42, "target": 25, "value": 45}, {"source": 42, "target": 41, "value": 69}, {"source": 43, "target": 42, "value": 51}, {"source": 46, "target": 39, "value": 2}, {"source": 47, "target": 46, "value": 12}, {"source": 44, "target": 43, "value": 10}, {"source": 39, "target": 44, "value": 5}, {"source": 2, "target": 32, "value": 6}, {"source": 29, "target": 15, "value": 1}, {"source": 22, "target": 45, "value": 574}, {"source": 21, "target": 11, "value": 893}, {"source": 24, "target": 10, "value": 172}, {"source": 23, "target": 13, "value": 25}, {"source": 27, "target": 7, "value": 487}, {"source": 26, "target": 9, "value": 635}, {"source": 45, "target": 34, "value": 19}, {"source": 9, "target": 40, "value": 5}, {"source": 13, "target": 33, "value": 1}, {"source": 10, "target": 29, "value": 4}, {"source": 11, "target": 0, "value": 7}, {"source": 31, "target": 40, "value": 9}, {"source": 16, "target": 40, "value": 1}, {"source": 19, "target": 48, "value": 2}, {"source": 20, "target": 33, "value": 1}, {"source": 17, "target": 29, "value": 1}, {"source": 18, "target": 0, "value": 2}, {"source": 3, "target": 13, "value": 15}, {"source": 4, "target": 17, "value": 69}, {"source": 38, "target": 11, "value": 1}, {"source": 13, "target": 8, "value": 17}, {"source": 1, "target": 9, "value": 1}, {"source": 47, "target": 24, "value": 1}, {"source": 48, "target": 17, "value": 1}, {"source": 6, "target": 15, "value": 116}, {"source": 34, "target": 40, "value": 78}, {"source": 0, "target": 34, "value": 67}, {"source": 48, "target": 33, "value": 41}, {"source": 5, "target": 48, "value": 161}, {"source": 29, "target": 0, "value": 99}, {"source": 33, "target": 29, "value": 32}, {"source": 0, "target": 31, "value": 15}, {"source": 34, "target": 32, "value": 25}, {"source": 0, "target": 16, "value": 2}, {"source": 33, "target": 18, "value": 2}, {"source": 48, "target": 36, "value": 8}, {"source": 33, "target": 37, "value": 6}, {"source": 29, "target": 30, "value": 39}, {"source": 38, "target": 18, "value": 63}, {"source": 33, "target": 11, "value": 2}]}